jaycode/__init__.py
jaycode/crawling.py
jaycode/db.py
jaycode/file.py
jaycode/ftp.py
jaycode/ssh.py
jaycode-0.2.1.dist-info/METADATA
jaycode-0.2.1.dist-info/WHEEL
jaycode-0.2.1.dist-info/top_level.txt
jaycode-0.2.1.dist-info/RECORD
