Metadata-Version: 2.4
Name: jaycode
Version: 0.2.1
Summary: Jay library
Author-email: 장동혁 <jangdonghyek@gmail.com>
Project-URL: Homepage, https://github.com/JangDongHyek/jaycode?tab=readme-ov-file#jaycode
Requires-Python: >=3.8
Requires-Dist: paramiko<3.0
Requires-Dist: pymysql
Requires-Dist: sshtunnel
Requires-Dist: ffmpeg-python
Requires-Dist: selenium>=4.10
